Metadata-Version: 2.1
Name: cdk-cloudformation-trendmicro-cloudonecontainer-helm
Version: 1.2.0a7
Summary: Deploys Trend Micro Cloud One Container Security into EKS clusters using helm.
Home-page: https://github.com/trendmicro/cloudone-container-security-helm/blob/master/README.md
Author: Amazon Web Services
License: Apache-2.0
Project-URL: Source, https://github.com/cdklabs/cdk-cloudformation.git
Platform: UNKNOWN
Classifier: Intended Audience :: Developers
Classifier: Operating System :: OS Independent
Classifier: Programming Language :: JavaScript
Classifier: Programming Language :: Python :: 3 :: Only
Classifier: Programming Language :: Python :: 3.7
Classifier: Programming Language :: Python :: 3.8
Classifier: Programming Language :: Python :: 3.9
Classifier: Programming Language :: Python :: 3.10
Classifier: Typing :: Typed
Classifier: License :: OSI Approved
Requires-Python: ~=3.7
License-File: LICENSE
Requires-Dist: aws-cdk-lib (<3.0.0,>=2.63.0)
Requires-Dist: constructs (<11.0.0,>=10.1.239)
Requires-Dist: jsii (<2.0.0,>=1.74.0)
Requires-Dist: publication (>=0.0.3)
Requires-Dist: typeguard (~=2.13.3)
